{
   "text": "Root",
    "children": [
        {
            "name": "A_mov6_measure122_ce1", 
            "icon": 'resources/images/mix_volume.png',
             "placement": "obvious",
               "children": [
                {
                    "icon": 'resources/images/details-xml.png',
                    "staff": "1",                   
                    "tstamp": "1",
                    "tstamp2": "m+6.5",
                    "place": "below",
                    "form": "cres",
                    "tag": "",
                    "leaf": true
                }
                ]            
        }, 
        {
            
            "name": "A_mov6_measure123_ce1",
            "icon": 'resources/images/mix_volume.png',
            "placement": "obvious",
            "children": [
                { 
                    "icon": 'resources/images/details-xml.png',
                    "staff": "1",
                    "tstamp": 2,
                    "tstamp2": "m+5",
                    "place": "below",
                    "form": "dim",
                     "tag": "",
                    "leaf": true
                }
            ]
        }
    ]
   }
  
     