{
   "text": "Root",
  
    "children": [
        {
            "name": "cres_1_below_obvious",
            "id": "12345678",
            "icon": 'resources/images/mix_volume.png',
             "obvious": true,
             "ambiguous": false,
               "children": [
                {
                    "icon": 'resources/images/details-xml.png',
                    "staff": "1",                   
                    "tstamp": "1",
                    "tstamp2": "m+6.5",
                    "place": "below",
                    "form": "cres",
                    "tag": "",
                    "leaf": true
                }
                ]            
        }, 
        {
            
            "name": "dim_1_below_obvious",
            "id": "elena",
            "icon": 'resources/images/mix_volume.png',
            "obvious": true,
            "ambiguous": false,
            "children": [
                { 
                    "icon": 'resources/images/details-xml.png',
                    "staff": "1",
                    "tstamp": 2,
                    "tstamp2": "m+5",
                    "place": "below",
                    "form": "dim",
                     "tag": "",
                    "leaf": true
                }
            ]
        }
    ]
   }
 